ocp/__init__.py
ocp/ocp_linux_arm64
ocp_linux_arm64-0.1.4.dist-info/LICENSE
ocp_linux_arm64-0.1.4.dist-info/METADATA
ocp_linux_arm64-0.1.4.dist-info/WHEEL
ocp_linux_arm64-0.1.4.dist-info/top_level.txt
ocp_linux_arm64-0.1.4.dist-info/RECORD
